uni_shift_reg/uni.v
module uni(
    input wire clk,
    input wire reset,
    input wire [1:0] op,
    input wire [3:0] d_in,
    input wire s_in,
    output reg [3:0] q
);

always @(posedge clk or posedge reset) begin
    if (reset)
        q <= 4'b0000;
    else begin
        case(op)
            2'b00: q <= q;                       // hold
            2'b01: q <= {q[2:0], s_in};          // shift left
            2'b10: q <= {s_in, q[3:1]};          // shift right
            2'b11: q <= d_in;                   // parallel load
        endcase
    end
end

endmodule

uni_shift_reg/uni_tb.v
module uni_tb();

reg [3:0] d_in;
reg s_in, reset;
reg [1:0] op;
reg clk;
wire [3:0] q;

uni ins(
    .d_in(d_in),
    .s_in(s_in),
    .reset(reset),
    .op(op),
    .clk(clk),
    .q(q)
);

// clock
initial begin
    clk = 0;
    forever #5 clk = ~clk;
end

// stimulus
initial begin
    reset = 1; s_in = 0; d_in = 0; op = 0; #10;
    reset = 0;

    // parallel load
    d_in = 4'b1001; op = 2'b11; #10;

    // shift left
    s_in = 1;
    op = 2'b01; #10;
    op = 2'b01; #10;

    // hold
    op = 2'b00; #10;

    // shift right
    s_in = 1;
    op = 2'b10; #10;
    s_in = 0;
    op = 2'b10; #10;

    $finish;
end

// monitor
initial begin
    $monitor("t=%0t q=%b op=%b s_in=%b", $time, q, op, s_in);
end

// waveform
initial begin
    $dumpfile("wave.vcd");
    $dumpvars(0, uni_tb);
end

endmodule

uni_shift_reg/wave.vcd
$date
	Sat Apr 18 21:53:15 2026
$end
$version
	Icarus Verilog
$end
$timescale
	1s
$end
$scope module uni_tb $end
$var wire 4 ! q [3:0] $end
$var reg 1 " clk $end
$var reg 4 # d_in [3:0] $end
$var reg 2 $ op [1:0] $end
$var reg 1 % reset $end
$var reg 1 & s_in $end
$scope module ins $end
$var wire 1 " clk $end
$var wire 4 ' d_in [3:0] $end
$var wire 2 ( op [1:0] $end
$var wire 1 % reset $end
$var wire 1 & s_in $end
$var reg 4 ) q [3:0] $end
$upscope $end
$upscope $end
$enddefinitions $end
$comment Show the parameter values. $end
$dumpall
$end
#0
$dumpvars
b0 )
b0 (
b0 '
0&
1%
b0 $
b0 #
0"
b0 !
$end
#5
1"
#10
0"
b11 $
b11 (
b1001 #
b1001 '
0%
#15
b1001 !
b1001 )
1"
#20
0"
b1 $
b1 (
1&
#25
b11 !
b11 )
1"
#30
0"
#35
b111 !
b111 )
1"
#40
0"
b0 $
b0 (
#45
1"
#50
0"
b10 $
b10 (
#55
b1011 !
b1011 )
1"
#60
0"
0&
#65
b101 !
b101 )
1"
